{

    "posts": [
        {
            "id": 1,
            "src": "/img/posts/man-in-forest.jpg",
            "description": "i am travelling",
            "tags": ["#forest", "#travel", "#journey", "#holiday"],
            "user": {
                "ava": "/img/avatars/01.png",
                "name": "Alex",
                "surname": "Alex"
            },

            "comments": [{
                "id": 1,
                "content": "some comment",
                "user": {
                    "ava": "/img/avatars/02.png",
                    "name": "Lu",
                    "surname": "Lu"
                }
            }]
        },

        {
            "id": 2,
            "src": "/img/posts/girl-pc.jpg",
            "description": "i am working",
            "tags": ["#work", "#travel", "#journey", "#computer"],
            "user": {
                "ava": "/img/avatars/01.png",
                "name": "Luba",
                "surname": "Loumer"
            },

            "comments": [{
                "id": 1,
                "content": "some comment",
                "user": {
                    "ava": "/img/avatars/01.png",
                    "name": "Lu",
                    "surname": "Lu"
                }
            }]
        }
    ]
}
